easy_bbox/__init__.py
easy_bbox/bbox.py
easy_bbox/py.typed
easy_bbox/utils.py
easy_bbox-1.0.4.dist-info/licenses/LICENSE
easy_bbox-1.0.4.dist-info/METADATA
easy_bbox-1.0.4.dist-info/WHEEL
easy_bbox-1.0.4.dist-info/top_level.txt
easy_bbox-1.0.4.dist-info/RECORD
