Metadata-Version: 2.4
Name: easy-bbox
Version: 1.0.4
Summary: A lightweight and easy bounding box manipulation library with Pascal VOC, COCO, and YOLO format conversions.
Author: Alex-experiments
License: MIT
Project-URL: Repository, https://github.com/Alex-experiments/easy-bbox
Project-URL: Documentation, https://alex-experiments.github.io/easy-bbox
Keywords: bounding-box,bbox,computer-vision,image-processing,object-detection,yolo,coco,pascal-voc,IoU
Classifier: Development Status :: 5 - Production/Stable
Classifier: Intended Audience :: Developers
Classifier: Topic :: Scientific/Engineering :: Image Processing
Classifier: Topic :: Software Development :: Libraries :: Python Modules
Classifier: License :: OSI Approved :: MIT License
Classifier: Programming Language :: Python :: 3
Classifier: Programming Language :: Python :: 3.9
Classifier: Programming Language :: Python :: 3.10
Classifier: Programming Language :: Python :: 3.11
Classifier: Programming Language :: Python :: 3.12
Requires-Python: >=3.9
License-File: LICENSE
Requires-Dist: pydantic>=2.0.0
Provides-Extra: dev
Requires-Dist: sphinx>=7.4.7; extra == "dev"
Requires-Dist: pytest>=7.0; extra == "dev"
Requires-Dist: pytest-cov; extra == "dev"
Requires-Dist: coverage; extra == "dev"
Requires-Dist: ruff; extra == "dev"
Requires-Dist: mypy; extra == "dev"
Requires-Dist: pre-commit; extra == "dev"
Requires-Dist: twine; extra == "dev"
Dynamic: license-file
